lund_pdf_master/OfficeToPDFConverter.py
lund_pdf_master/__init__.py
tests/__init__.py
tests/test_api.py
LundPDFMaster-1.1.2.dist-info/LICENSE.txt
LundPDFMaster-1.1.2.dist-info/METADATA
LundPDFMaster-1.1.2.dist-info/WHEEL
LundPDFMaster-1.1.2.dist-info/top_level.txt
LundPDFMaster-1.1.2.dist-info/RECORD
