Metadata-Version: 2.1
Name: LundPDFMaster
Version: 1.1.2
Summary: A Python library for converting office files to PDF using the iLovePDF API
Home-page: https://github.com/LundIT/LundPDFMaster
Author: Ensar Kaya
Author-email: e.kaya@lund-it.com
License: UNKNOWN
Platform: UNKNOWN
Classifier: Programming Language :: Python :: 3
Classifier: License :: OSI Approved :: MIT License
Classifier: Operating System :: OS Independent
Requires-Python: >=3.6
License-File: LICENSE.txt
Requires-Dist: requests
